{"color":{"phoenix-blue":{"description":"#6CD7EB","type":"color","value":"#6cd7ebff","blendMode":"normal","extensions":{"org.lukasoppermann.figmaDesignTokens":{"styleId":"S:9452090d66f8f869952aa68c3b01d0ffda1f9aa2,","exportKey":"color"}}},"phoenix-yellow":{"description":"#FFC600","type":"color","value":"#ffc600ff","blendMode":"normal","extensions":{"org.lukasoppermann.figmaDesignTokens":{"styleId":"S:086f998b826da310f6f0a3f9e87aa6a644c13d89,","exportKey":"color"}}},"phoenix-black":{"description":"#000000","type":"color","value":"#000000ff","blendMode":"normal","extensions":{"org.lukasoppermann.figmaDesignTokens":{"styleId":"S:f0a67fb33dc887bd74e93e05e0772ce10afaf1d4,","exportKey":"color"}}},"daytona-blue":{"description":"#00ADEF","type":"color","value":"#00adefff","blendMode":"normal","extensions":{"org.lukasoppermann.figmaDesignTokens":{"styleId":"S:0dd507057873e891177bdf6e72f686d610c7261e,","exportKey":"color"}}},"daytona-red":{"description":"#EF4035","type":"color","value":"#ef4035ff","blendMode":"normal","extensions":{"org.lukasoppermann.figmaDesignTokens":{"styleId":"S:1b3ec8df79b30b3014df9e34cf9dc4ad956cfb2f,","exportKey":"color"}}},"daytona-yellow":{"description":"#FFF300","type":"color","value":"#fff300ff","blendMode":"normal","extensions":{"org.lukasoppermann.figmaDesignTokens":{"styleId":"S:c1762343daa9d3551909aa0f48ab5690effd526d,","exportKey":"color"}}},"daytona-green":{"description":"#1FB25A","type":"color","value":"#1fb25aff","blendMode":"normal","extensions":{"org.lukasoppermann.figmaDesignTokens":{"styleId":"S:48fd537e7921cd4d106e9d7e3ae3a512925a8ede,","exportKey":"color"}}},"talladega-red":{"description":"#B2121A","type":"color","value":"#b2121aff","blendMode":"normal","extensions":{"org.lukasoppermann.figmaDesignTokens":{"styleId":"S:50543feb8e57682eb70e1bc46219dc0c8523b3ed,","exportKey":"color"}}},"talladega-light-grey":{"description":"#EBEBEB","type":"color","value":"#ebebebff","blendMode":"normal","extensions":{"org.lukasoppermann.figmaDesignTokens":{"styleId":"S:6db5d29ab978ccdc4d8953240163d9f9e0939ea1,","exportKey":"color"}}},"homestead-pink":{"description":"#EA0A8C","type":"color","value":"#ea0a8cff","blendMode":"normal","extensions":{"org.lukasoppermann.figmaDesignTokens":{"styleId":"S:d0c9c908cc85fa3095bb30e32e0bb6d6068bfea2,","exportKey":"color"}}},"homestead-dark-turquoise":{"description":"#054944","type":"color","value":"#054944ff","blendMode":"normal","extensions":{"org.lukasoppermann.figmaDesignTokens":{"styleId":"S:32c6656d1419d09a6b6a1ec0279ee9994cda45d8,","exportKey":"color"}}},"homestead-yellow":{"description":"#FFB52A","type":"color","value":"#ffb52aff","blendMode":"normal","extensions":{"org.lukasoppermann.figmaDesignTokens":{"styleId":"S:eab165885cd195ca36a57325094991caa816bed8,","exportKey":"color"}}},"homestead-light-turquoise":{"description":"#00C8B9","type":"color","value":"#00c8b9ff","blendMode":"normal","extensions":{"org.lukasoppermann.figmaDesignTokens":{"styleId":"S:d74adac153ae4c80b677ff5c33c232cda51f4272,","exportKey":"color"}}},"homestead-blue":{"description":"#27AAE1","type":"color","value":"#27aae1ff","blendMode":"normal","extensions":{"org.lukasoppermann.figmaDesignTokens":{"styleId":"S:f7b5bd0e5fb35717b79f0e43bc59f5d01219b733,","exportKey":"color"}}},"watkins-glen-blue":{"description":"#009DDC","type":"color","value":"#009ddcff","blendMode":"normal","extensions":{"org.lukasoppermann.figmaDesignTokens":{"styleId":"S:ad5d626142f79250d852eee60e6640674fce7a52,","exportKey":"color"}}},"watkins-glen-red":{"description":"#EE2E24","type":"color","value":"#ee2e24ff","blendMode":"normal","extensions":{"org.lukasoppermann.figmaDesignTokens":{"styleId":"S:50526f836c9d86e85cfe44279e6c641295ff921d,","exportKey":"color"}}},"kansas-blue":{"description":"#2C4187","type":"color","value":"#2c4187ff","blendMode":"normal","extensions":{"org.lukasoppermann.figmaDesignTokens":{"styleId":"S:fab427eb304eea8a48311a896fa728c39fb7039d,","exportKey":"color"}}},"kansas-yellow":{"description":"#F1CA2D","type":"color","value":"#f1ca2dff","blendMode":"normal","extensions":{"org.lukasoppermann.figmaDesignTokens":{"styleId":"S:213797824c7e846ef9cb1cd6e3a803ccb298d0ce,","exportKey":"color"}}},"martinsville-red":{"description":"#EA2035","type":"color","value":"#ea2035ff","blendMode":"normal","extensions":{"org.lukasoppermann.figmaDesignTokens":{"styleId":"S:47cd334b7af91801a19418ad71d89afc2dcdcfc7,","exportKey":"color"}}},"darlington-burgundy":{"description":"#7F0528","type":"color","value":"#7f0528ff","blendMode":"normal","extensions":{"org.lukasoppermann.figmaDesignTokens":{"styleId":"S:cf409df02ceedf13d41c9e8a2cd03a543a9adc3e,","exportKey":"color"}}},"richmond-red":{"description":"#EB0029","type":"color","value":"#eb0029ff","blendMode":"normal","extensions":{"org.lukasoppermann.figmaDesignTokens":{"styleId":"S:59cead0969e732e7ec8d62e569c76ba191504387,","exportKey":"color"}}},"richmond-light-grey":{"description":"#E6E7E8","type":"color","value":"#e6e7e8ff","blendMode":"normal","extensions":{"org.lukasoppermann.figmaDesignTokens":{"styleId":"S:1e3ab0eb8cbd9d492458168f9a729ee1bf8e22e7,","exportKey":"color"}}},"richmond-dark-grey":{"description":"#636466","type":"color","value":"#636466ff","blendMode":"normal","extensions":{"org.lukasoppermann.figmaDesignTokens":{"styleId":"S:d391e38d9bfe351d40ad36403b7b1c0468cd37bd,","exportKey":"color"}}},"route66-dark-grey":{"description":"#383838","type":"color","value":"#383838ff","blendMode":"normal","extensions":{"org.lukasoppermann.figmaDesignTokens":{"styleId":"S:c046f827cc9bdc7485d4fd98f371a13b4b28774c,","exportKey":"color"}}},"route66-red":{"description":"#BB2930","type":"color","value":"#bb2930ff","blendMode":"normal","extensions":{"org.lukasoppermann.figmaDesignTokens":{"styleId":"S:9e4044bacf1f5f98475c5aedda3c3d13bfe29bf7,","exportKey":"color"}}},"michigan-navy":{"description":"#002B49","type":"color","value":"#002b49ff","blendMode":"normal","extensions":{"org.lukasoppermann.figmaDesignTokens":{"styleId":"S:aec69e9d84fdd7e2340f0660080270763091ba3e,","exportKey":"color"}}},"michigan-green":{"description":"#07A23F","type":"color","value":"#07a23fff","blendMode":"normal","extensions":{"org.lukasoppermann.figmaDesignTokens":{"styleId":"S:e80eded61a1d61efd6b3b688bd2f61787c219a86,","exportKey":"color"}}},"michigan-light-blue":{"description":"#00A9E0","type":"color","value":"#00a9e0ff","blendMode":"normal","extensions":{"org.lukasoppermann.figmaDesignTokens":{"styleId":"S:948534326b36060fb69ef2f8af5e03fc85c17850,","exportKey":"color"}}},"michigan-orange":{"description":"#E87722","type":"color","value":"#e87722ff","blendMode":"normal","extensions":{"org.lukasoppermann.figmaDesignTokens":{"styleId":"S:505bdc17ac2df159e46dd6e17ae3451a7732df2e,","exportKey":"color"}}}}}